{
  "hash": "4c924960",
  "browserHash": "57131d54",
  "optimized": {
    "vue": {
      "src": "../../../../../node_modules/.pnpm/vue@3.2.45/node_modules/vue/dist/vue.runtime.esm-bundler.js",
      "file": "vue.js",
      "fileHash": "6c3f5b9f",
      "needsInterop": false
    },
    "dayjs": {
      "src": "../../../../../node_modules/.pnpm/dayjs@1.11.7/node_modules/dayjs/dayjs.min.js",
      "file": "dayjs.js",
      "fileHash": "9c44711c",
      "needsInterop": true
    },
    "dayjs/plugin/localeData.js": {
      "src": "../../../../../node_modules/.pnpm/dayjs@1.11.7/node_modules/dayjs/plugin/localeData.js",
      "file": "dayjs_plugin_localeData__js.js",
      "fileHash": "c4495d23",
      "needsInterop": true
    },
    "dayjs/plugin/advancedFormat.js": {
      "src": "../../../../../node_modules/.pnpm/dayjs@1.11.7/node_modules/dayjs/plugin/advancedFormat.js",
      "file": "dayjs_plugin_advancedFormat__js.js",
      "fileHash": "e01504aa",
      "needsInterop": true
    },
    "dayjs/plugin/customParseFormat.js": {
      "src": "../../../../../node_modules/.pnpm/dayjs@1.11.7/node_modules/dayjs/plugin/customParseFormat.js",
      "file": "dayjs_plugin_customParseFormat__js.js",
      "fileHash": "c4b0e22c",
      "needsInterop": true
    },
    "dayjs/plugin/weekOfYear.js": {
      "src": "../../../../../node_modules/.pnpm/dayjs@1.11.7/node_modules/dayjs/plugin/weekOfYear.js",
      "file": "dayjs_plugin_weekOfYear__js.js",
      "fileHash": "3ac4defe",
      "needsInterop": true
    },
    "dayjs/plugin/weekYear.js": {
      "src": "../../../../../node_modules/.pnpm/dayjs@1.11.7/node_modules/dayjs/plugin/weekYear.js",
      "file": "dayjs_plugin_weekYear__js.js",
      "fileHash": "7da97560",
      "needsInterop": true
    },
    "dayjs/plugin/dayOfYear.js": {
      "src": "../../../../../node_modules/.pnpm/dayjs@1.11.7/node_modules/dayjs/plugin/dayOfYear.js",
      "file": "dayjs_plugin_dayOfYear__js.js",
      "fileHash": "8657c5ea",
      "needsInterop": true
    },
    "dayjs/plugin/isSameOrAfter.js": {
      "src": "../../../../../node_modules/.pnpm/dayjs@1.11.7/node_modules/dayjs/plugin/isSameOrAfter.js",
      "file": "dayjs_plugin_isSameOrAfter__js.js",
      "fileHash": "3a9c3ed6",
      "needsInterop": true
    },
    "dayjs/plugin/isSameOrBefore.js": {
      "src": "../../../../../node_modules/.pnpm/dayjs@1.11.7/node_modules/dayjs/plugin/isSameOrBefore.js",
      "file": "dayjs_plugin_isSameOrBefore__js.js",
      "fileHash": "a1ac78aa",
      "needsInterop": true
    },
    "@vueuse/core": {
      "src": "../../../../../node_modules/.pnpm/@vueuse+core@9.10.0_vue@3.2.45/node_modules/@vueuse/core/index.mjs",
      "file": "@vueuse_core.js",
      "fileHash": "cfa3bc10",
      "needsInterop": false
    },
    "clipboard-copy": {
      "src": "../../../../../node_modules/.pnpm/clipboard-copy@4.0.1/node_modules/clipboard-copy/index.js",
      "file": "clipboard-copy.js",
      "fileHash": "85313d8f",
      "needsInterop": true
    },
    "lodash-unified": {
      "src": "../../../../../node_modules/.pnpm/lodash-unified@1.0.3_3ib2ivapxullxkx3xftsimdk7u/node_modules/lodash-unified/import.js",
      "file": "lodash-unified.js",
      "fileHash": "030e9125",
      "needsInterop": false
    },
    "@ctrl/tinycolor": {
      "src": "../../../../../node_modules/.pnpm/@ctrl+tinycolor@3.6.0/node_modules/@ctrl/tinycolor/dist/module/public_api.js",
      "file": "@ctrl_tinycolor.js",
      "fileHash": "a5dbbe27",
      "needsInterop": false
    }
  },
  "chunks": {
    "chunk-PEVCE5PM": {
      "file": "chunk-PEVCE5PM.js"
    },
    "chunk-RSJERJUL": {
      "file": "chunk-RSJERJUL.js"
    }
  }
}